higher_spectrum-0.3.0.dist-info/licenses/LICENSE
spectrum/__init__.py
spectrum/armafit.py
spectrum/armasel.py
spectrum/bicoherence.py
spectrum/bicoherencex.py
spectrum/bispectrumd.py
spectrum/bispectrumdx.py
spectrum/bispectrumi.py
spectrum/cum2est.py
spectrum/cum2x.py
spectrum/cum3est.py
spectrum/cum3x.py
spectrum/cum4est.py
spectrum/cum4x.py
spectrum/cumest.py
spectrum/harmgen.py
spectrum/nlgen.py
spectrum/trispectrum.py
spectrum/tools/__init__.py
spectrum/tools/matlab.py
spectrum/tools/types.py
higher_spectrum-0.3.0.dist-info/METADATA
higher_spectrum-0.3.0.dist-info/WHEEL
higher_spectrum-0.3.0.dist-info/top_level.txt
higher_spectrum-0.3.0.dist-info/RECORD
