Metadata-Version: 2.4
Name: higher-spectrum
Version: 0.3.0
Summary: Higher Order Spectral Analysis toolkit
Home-page: https://github.com/synergetics/spectrum
Author: ixaxaar
Author-email: root@ixaxaar.in
License: MIT
Keywords: higher order spectrum estimation toolkit signal processing
Classifier: Development Status :: 5 - Production/Stable
Classifier: Intended Audience :: Science/Research
Classifier: License :: OSI Approved :: MIT License
Classifier: Programming Language :: Python :: 3
Classifier: Programming Language :: Python :: 3.6
Classifier: Programming Language :: Python :: 3.7
Classifier: Programming Language :: Python :: 3.8
Classifier: Programming Language :: Python :: 3.9
Classifier: Topic :: Scientific/Engineering :: Information Analysis
Requires-Python: >=3.6
License-File: LICENSE
Requires-Dist: numpy>=1.18.0
Requires-Dist: scipy>=1.4.0
Requires-Dist: matplotlib>=3.1.0
Dynamic: author
Dynamic: author-email
Dynamic: classifier
Dynamic: description
Dynamic: description-content-type
Dynamic: home-page
Dynamic: keywords
Dynamic: license
Dynamic: license-file
Dynamic: requires-dist
Dynamic: requires-python
Dynamic: summary
